vatic/__init__.py
vatic/__main__.py
vatic/cli.py
vatic/kalshi.py
vatic/manifold.py
vatic/metaculus.py
vatic/predictit.py
vatic-0.0.4.dist-info/LICENSE
vatic-0.0.4.dist-info/METADATA
vatic-0.0.4.dist-info/WHEEL
vatic-0.0.4.dist-info/entry_points.txt
vatic-0.0.4.dist-info/top_level.txt
vatic-0.0.4.dist-info/RECORD
