Metadata-Version: 2.1
Name: vatic
Version: 0.0.4
Summary: Interface with prediction markets
Home-page: https://vatic.readthedocs.io/
Author: Scott Lawrence
Author-email: scott.lawrence-1@colorado.edu
Project-URL: Repository, https://gitlab.com/s.lawrence/vatic
Classifier: Programming Language :: Python :: 3
Classifier: Operating System :: OS Independent
License-File: LICENSE
Requires-Dist: httpx (>=0.23)
Requires-Dist: tqdm (>=4.64)
